cellml.recipe.api-0.8-py2.7-nspkg.pth
cellml/recipe/api/README.rst
cellml/recipe/api/__init__.py
cellml/recipe/api/tests/__init__.py
cellml/recipe/api/tests/test_docs.py
cellml.recipe.api-0.8.dist-info/COPYING.txt
cellml.recipe.api-0.8.dist-info/METADATA
cellml.recipe.api-0.8.dist-info/WHEEL
cellml.recipe.api-0.8.dist-info/entry_points.txt
cellml.recipe.api-0.8.dist-info/namespace_packages.txt
cellml.recipe.api-0.8.dist-info/top_level.txt
cellml.recipe.api-0.8.dist-info/RECORD
