Metadata-Version: 2.1
Name: cellml.recipe.api
Version: 0.8
Summary: Recipe to call CMake to build CellML API and Python bindings
Home-page: http://www.cellml.org/tools/api/
Author: Tommy Yu
Author-email: tommy.yu@auckland.ac.nz
License: GPL/LGPL/MPL
Keywords: cellml
Platform: UNKNOWN
Classifier: Framework :: Buildout :: Recipe
Classifier: Intended Audience :: Developers
Classifier: Topic :: Software Development :: Build Tools
Classifier: Topic :: Software Development :: Libraries :: Python Modules
Classifier: License :: OSI Approved :: GNU General Public License (GPL)
Classifier: License :: OSI Approved :: GNU Library or Lesser General Public License (LGPL)
Classifier: License :: OSI Approved :: Mozilla Public License 1.1 (MPL 1.1)
Requires-Dist: setuptools
Requires-Dist: zc.buildout
Requires-Dist: zc.recipe.cmmi
Provides-Extra: tests
Requires-Dist: zope.testing ; extra == 'tests'
Requires-Dist: zc.buildout ; extra == 'tests'
